MANIFEST.in
pavement.py
setup.cfg
setup.py
staticlxml/__init__.py
staticlxml.egg-info/PKG-INFO
staticlxml.egg-info/SOURCES.txt
staticlxml.egg-info/dependency_links.txt
staticlxml.egg-info/entry_points.txt
staticlxml.egg-info/not-zip-safe
staticlxml.egg-info/top_level.txt