Metadata-Version: 1.0
Name: staticlxml
Version: 0.1.2
Summary: A simple way to install lxml in a static manner
Home-page: http://www.percious.com
Author: Christopher Perkins
Author-email: chris@percious.com
License: BSD
Platform: UNKNOWN
Classifier: Development Status :: 3 - Alpha
Classifier: Intended Audience :: Developers
Classifier: Programming Language :: Python
Classifier: Topic :: Internet :: WWW/HTTP
Classifier: Topic :: Internet :: WWW/HTTP :: Dynamic Content
Classifier: Topic :: Internet :: WWW/HTTP :: WSGI
Classifier: Topic :: Internet :: WWW/HTTP :: WSGI :: Application
